LICENSE
LICENSE.txt
MANIFEST.in
README.md
setup.cfg
setup.py
custom_calc_sdp/__init__.py
custom_calc_sdp/app.py
custom_calc_sdp/mycalculator.py
custom_calc_sdp.egg-info/PKG-INFO
custom_calc_sdp.egg-info/SOURCES.txt
custom_calc_sdp.egg-info/dependency_links.txt
custom_calc_sdp.egg-info/entry_points.txt
custom_calc_sdp.egg-info/requires.txt
custom_calc_sdp.egg-info/top_level.txt
custom_calc_sdp/static/index.html
custom_calc_sdp/static/css/main.css
custom_calc_sdp/static/css/style.css
custom_calc_sdp/templates/index.html
custom_calc_sdp/templates/results.html